django_better_image/__init__.py
django_better_image/fields.py
django_better_image/formfields.py
django_better_image/forms.py
django_better_image/urls.py
django_better_image/views.py
django_better_image/widgets.py
django_better_image/templatetags/__init__.py
django_better_image/templatetags/django_better_image.py
django_better_image-0.0.5.dist-info/LICENSE
django_better_image-0.0.5.dist-info/METADATA
django_better_image-0.0.5.dist-info/WHEEL
django_better_image-0.0.5.dist-info/top_level.txt
django_better_image-0.0.5.dist-info/RECORD
